{
    "@class": "com.kony.gen.viz.model.component.KVizDateField",
    "DNDConfig": null,
    "Image": "calbtn.png",
    "_data_": null,
    "_date_": "3/12/2024",
    "_height_": {
        "type": "string",
        "value": "40dp"
    },
    "_left_": {
        "type": "string",
        "value": "0"
    },
    "_margin_": [
        0,
        0,
        0,
        0
    ],
    "_padding_": [
        0,
        0,
        0,
        0
    ],
    "_skin_": "s336d1b17ab547c089674309fc779c7f",
    "_top_": {
        "type": "string",
        "value": "0"
    },
    "_width_": {
        "type": "string",
        "value": "5%"
    },
    "advview": "default",
    "calendaricon": "calbtn.png",
    "canUpdateUI": true,
    "containerweight": 100,
    "contentalignment": 6,
    "datecomponents": [
        3,
        12,
        2024,
        0,
        0,
        0
    ],
    "dateeditable": true,
    "dateformat": "dd/MM/yyyy",
    "day": 3,
    "daytextalignmentincell": 5,
    "format": "dd/MM/yyyy",
    "formatteddate": "03/12/2024",
    "hidedaysheader": false,
    "hidemonthsheader": false,
    "hour": 0,
    "id": "calDOB",
    "info": null,
    "iscustomlayout": false,
    "isvisible": true,
    "kuid": "g93a46684cac42a6a20e0bf37ee8e4a9",
    "minutes": 0,
    "month": 12,
    "name": "kony.ui.Calendar",
    "noofmonths": 1,
    "pagedate": "/2024",
    "parent": "fcDOB",
    "pf": "frmPatientDetails",
    "retaincontentalignment": false,
    "retainflexpositionproperties": false,
    "seconds": 0,
    "selectdate": "//2024",
    "viewtype": "default",
    "wType": "Calendar",
    "widgetalignment": 5,
    "year": 2024
}